self_encryption-0.32.41.dist-info/METADATA
self_encryption-0.32.41.dist-info/WHEEL
self_encryption-0.32.41.dist-info/licenses/LICENSE
self_encryption/cli.py
self_encryption/__init__.py
self_encryption/self_encryption.cp312-win_amd64.pyd
self_encryption-0.32.41.dist-info/RECORD
