Metadata-Version: 2.3
Name: self_encryption
Version: 0.32.41
Classifier: Programming Language :: Python :: 3
Classifier: Programming Language :: Rust
Classifier: Operating System :: OS Independent
License-File: LICENSE
Summary: Python bindings for self-encryption library
Home-Page: https://maidsafe.net
Author: MaidSafe Developers <dev@maidsafe.net>
Author-email: David Irvine <david.irvine@maidsafe.net>
License: GPL-3.0
Requires-Python: >=3.7
Project-URL: Source Code, https://github.com/maidsafe/self_encryption
